<?xml version="1.0" encoding="utf-8"?>
<kAIXmlBehaviour xmlns:i="http://www.w3.org/2001/XMLSchema-instance" xmlns="http://schemas.datacontract.org/2004/07/kAI.Core">
  <BehaviourID>StandardShipAI</BehaviourID>
  <InternalConnexions>
    <kAIXmlBehaviour.InternalXml.SerialConnexion>
      <EndNodeID>
        <NodeID>ShipEngineController</NodeID>
      </EndNodeID>
      <EndPortID>
        <PortID>Velocity</PortID>
      </EndPortID>
      <StartNodeID>
        <NodeID>HandleMoveOrder</NodeID>
      </StartNodeID>
      <StartPortID>
        <PortID>Velocity</PortID>
      </StartPortID>
    </kAIXmlBehaviour.InternalXml.SerialConnexion>
    <kAIXmlBehaviour.InternalXml.SerialConnexion>
      <EndNodeID>
        <NodeID>HandleMoveOrder</NodeID>
      </EndNodeID>
      <EndPortID>
        <PortID>Activate</PortID>
      </EndPortID>
      <StartNodeID>
        <NodeID>OrderSwitcherBehaviour</NodeID>
      </StartNodeID>
      <StartPortID>
        <PortID>MoveOrder</PortID>
      </StartPortID>
    </kAIXmlBehaviour.InternalXml.SerialConnexion>
    <kAIXmlBehaviour.InternalXml.SerialConnexion>
      <EndNodeID>
        <NodeID>HandleMoveOrder</NodeID>
      </EndNodeID>
      <EndPortID>
        <PortID>Deactivate</PortID>
      </EndPortID>
      <StartNodeID>
        <NodeID>OrderSwitcherBehaviour</NodeID>
      </StartNodeID>
      <StartPortID>
        <PortID>AttackOrder</PortID>
      </StartPortID>
    </kAIXmlBehaviour.InternalXml.SerialConnexion>
    <kAIXmlBehaviour.InternalXml.SerialConnexion>
      <EndNodeID>
        <NodeID>HandleMoveOrder</NodeID>
      </EndNodeID>
      <EndPortID>
        <PortID>Target</PortID>
      </EndPortID>
      <StartNodeID>
        <NodeID>OrderDataExtractor</NodeID>
      </StartNodeID>
      <StartPortID>
        <PortID>Destination</PortID>
      </StartPortID>
    </kAIXmlBehaviour.InternalXml.SerialConnexion>
    <kAIXmlBehaviour.InternalXml.SerialConnexion>
      <EndNodeID>
        <NodeID>OrderSwitcherBehaviour</NodeID>
      </EndNodeID>
      <EndPortID>
        <PortID>Activate</PortID>
      </EndPortID>
      <StartNodeID>
        <NodeID>InvalidNode</NodeID>
      </StartNodeID>
      <StartPortID>
        <PortID>OnActivate</PortID>
      </StartPortID>
    </kAIXmlBehaviour.InternalXml.SerialConnexion>
    <kAIXmlBehaviour.InternalXml.SerialConnexion>
      <EndNodeID>
        <NodeID>OrderDataExtractor</NodeID>
      </EndNodeID>
      <EndPortID>
        <PortID>Activate</PortID>
      </EndPortID>
      <StartNodeID>
        <NodeID>InvalidNode</NodeID>
      </StartNodeID>
      <StartPortID>
        <PortID>OnActivate</PortID>
      </StartPortID>
    </kAIXmlBehaviour.InternalXml.SerialConnexion>
    <kAIXmlBehaviour.InternalXml.SerialConnexion>
      <EndNodeID>
        <NodeID>ShipEngineController</NodeID>
      </EndNodeID>
      <EndPortID>
        <PortID>Activate</PortID>
      </EndPortID>
      <StartNodeID>
        <NodeID>InvalidNode</NodeID>
      </StartNodeID>
      <StartPortID>
        <PortID>OnActivate</PortID>
      </StartPortID>
    </kAIXmlBehaviour.InternalXml.SerialConnexion>
    <kAIXmlBehaviour.InternalXml.SerialConnexion>
      <EndNodeID>
        <NodeID>OrderSwitcherBehaviour</NodeID>
      </EndNodeID>
      <EndPortID>
        <PortID>Order</PortID>
      </EndPortID>
      <StartNodeID>
        <NodeID>InvalidNode</NodeID>
      </StartNodeID>
      <StartPortID>
        <PortID>Order</PortID>
      </StartPortID>
    </kAIXmlBehaviour.InternalXml.SerialConnexion>
    <kAIXmlBehaviour.InternalXml.SerialConnexion>
      <EndNodeID>
        <NodeID>OrderDataExtractor</NodeID>
      </EndNodeID>
      <EndPortID>
        <PortID>Order</PortID>
      </EndPortID>
      <StartNodeID>
        <NodeID>InvalidNode</NodeID>
      </StartNodeID>
      <StartPortID>
        <PortID>Order</PortID>
      </StartPortID>
    </kAIXmlBehaviour.InternalXml.SerialConnexion>
  </InternalConnexions>
  <InternalNodes>
    <kAIXmlBehaviour.InternalXml.SerialNode>
      <NodeContents i:type="kAIXmlBehaviour.SerialObject">
        <BehaviourID>
          <BehaviourID>HandleMoveOrder</BehaviourID>
        </BehaviourID>
        <XmlBehaviourFile>
          <Path>\HandleMoveOrder.xml</Path>
          <RootID>Behaviour:StandardShipAI</RootID>
        </XmlBehaviourFile>
      </NodeContents>
      <NodeID>
        <NodeID>HandleMoveOrder</NodeID>
      </NodeID>
      <NodeSerialAssembly>kAICore</NodeSerialAssembly>
      <NodeSerialType>kAI.Core.kAIXmlBehaviour+SerialObject</NodeSerialType>
      <NodeType>kAI.Core.kAIXmlBehaviour</NodeType>
      <NodeTypeAssembly>kAICore</NodeTypeAssembly>
    </kAIXmlBehaviour.InternalXml.SerialNode>
    <kAIXmlBehaviour.InternalXml.SerialNode>
      <NodeContents i:type="kAICodeBehaviour.SerialObject">
        <BehaviourAssembly>Assembly-CSharp</BehaviourAssembly>
        <BehaviourID>ShipEngineController</BehaviourID>
        <BehaviourType>ShipEngineController</BehaviourType>
      </NodeContents>
      <NodeID>
        <NodeID>ShipEngineController</NodeID>
      </NodeID>
      <NodeSerialAssembly>kAICore</NodeSerialAssembly>
      <NodeSerialType>kAI.Core.kAICodeBehaviour+SerialObject</NodeSerialType>
      <NodeType>ShipEngineController</NodeType>
      <NodeTypeAssembly>Assembly-CSharp</NodeTypeAssembly>
    </kAIXmlBehaviour.InternalXml.SerialNode>
    <kAIXmlBehaviour.InternalXml.SerialNode>
      <NodeContents i:type="kAICodeBehaviour.SerialObject">
        <BehaviourAssembly>Assembly-CSharp</BehaviourAssembly>
        <BehaviourID>OrderSwitcherBehaviour</BehaviourID>
        <BehaviourType>OrderSwitcherBehaviour</BehaviourType>
      </NodeContents>
      <NodeID>
        <NodeID>OrderSwitcherBehaviour</NodeID>
      </NodeID>
      <NodeSerialAssembly>kAICore</NodeSerialAssembly>
      <NodeSerialType>kAI.Core.kAICodeBehaviour+SerialObject</NodeSerialType>
      <NodeType>OrderSwitcherBehaviour</NodeType>
      <NodeTypeAssembly>Assembly-CSharp</NodeTypeAssembly>
    </kAIXmlBehaviour.InternalXml.SerialNode>
    <kAIXmlBehaviour.InternalXml.SerialNode>
      <NodeContents i:type="kAICodeBehaviour.SerialObject">
        <BehaviourAssembly>Assembly-CSharp</BehaviourAssembly>
        <BehaviourID>OrderDataExtractor</BehaviourID>
        <BehaviourType>OrderDataExtractor</BehaviourType>
      </NodeContents>
      <NodeID>
        <NodeID>OrderDataExtractor</NodeID>
      </NodeID>
      <NodeSerialAssembly>kAICore</NodeSerialAssembly>
      <NodeSerialType>kAI.Core.kAICodeBehaviour+SerialObject</NodeSerialType>
      <NodeType>OrderDataExtractor</NodeType>
      <NodeTypeAssembly>Assembly-CSharp</NodeTypeAssembly>
    </kAIXmlBehaviour.InternalXml.SerialNode>
  </InternalNodes>
  <InternalPorts>
    <kAIXmlBehaviour.InternalXml.SerialPort>
      <IsGloballyAccesible>false</IsGloballyAccesible>
      <PortDataType>System.Boolean</PortDataType>
      <PortDataTypeAssembly>mscorlib</PortDataTypeAssembly>
      <PortDirection>PortDirection_Out</PortDirection>
      <PortID>OnActivate</PortID>
      <PortIsTrigger>true</PortIsTrigger>
    </kAIXmlBehaviour.InternalXml.SerialPort>
    <kAIXmlBehaviour.InternalXml.SerialPort>
      <IsGloballyAccesible>false</IsGloballyAccesible>
      <PortDataType>System.Boolean</PortDataType>
      <PortDataTypeAssembly>mscorlib</PortDataTypeAssembly>
      <PortDirection>PortDirection_In</PortDirection>
      <PortID>Deactivate</PortID>
      <PortIsTrigger>true</PortIsTrigger>
    </kAIXmlBehaviour.InternalXml.SerialPort>
    <kAIXmlBehaviour.InternalXml.SerialPort>
      <IsGloballyAccesible>true</IsGloballyAccesible>
      <PortDataType>IndividualOrder</PortDataType>
      <PortDataTypeAssembly>Assembly-CSharp</PortDataTypeAssembly>
      <PortDirection>PortDirection_Out</PortDirection>
      <PortID>Order</PortID>
      <PortIsTrigger>false</PortIsTrigger>
    </kAIXmlBehaviour.InternalXml.SerialPort>
  </InternalPorts>
</kAIXmlBehaviour>